djangocopypaste/__init__.py
djangocopypaste/validators.py
djangocopypaste-0.1.1.dist-info/METADATA
djangocopypaste-0.1.1.dist-info/RECORD
djangocopypaste-0.1.1.dist-info/WHEEL
djangocopypaste-0.1.1.dist-info/top_level.txt
